xbridge/__init__.py
xbridge/__main__.py
xbridge-1.2.0.dist-info/LICENSE
xbridge-1.2.0.dist-info/WHEEL
xbridge-1.2.0.dist-info/entry_points.txt
xbridge-1.2.0.dist-info/METADATA
xbridge-1.2.0.dist-info/RECORD
