Metadata-Version: 2.1
Name: xbridge
Version: 1.2.0
Summary: A Securely Data Transmitting Tool
License: MIT
Author: yudingp
Author-email: yudingp@163.com
Requires-Python: >=3.8,<4.0
Classifier: License :: OSI Approved :: MIT License
Classifier: Programming Language :: Python :: 3
Classifier: Programming Language :: Python :: 3.8
Classifier: Programming Language :: Python :: 3.9
Classifier: Programming Language :: Python :: 3.10
Classifier: Programming Language :: Python :: 3.11
Requires-Dist: oorpc (>=0.1.3,<0.2.0)
